wsvnc/__init__.py
wsvnc/color.py
wsvnc/constants.py
wsvnc/pixel_format.py
wsvnc/py.typed
wsvnc/rectangle.py
wsvnc/encodings/__init__.py
wsvnc/encodings/copyrect_encoding.py
wsvnc/encodings/encoding_interface.py
wsvnc/encodings/pseudo_desktop_size_encoding.py
wsvnc/encodings/raw_encoding.py
wsvnc/encodings/tightdiff_comp_encoding.py
wsvnc/encodings/tightpng_encoding.py
wsvnc/encodings/tightpng_encoding_jpeg_10.py
wsvnc/encodings/vmware_define_cursor_encoding.py
wsvnc/exceptions/__init__.py
wsvnc/exceptions/encoding_exception.py
wsvnc/rfb/__init__.py
wsvnc/rfb/rfb_client.py
wsvnc/security/__init__.py
wsvnc/security/no_security.py
wsvnc/security/security_type_interface.py
wsvnc/security/vnc_security.py
wsvnc/server_messages/__init__.py
wsvnc/server_messages/bell.py
wsvnc/server_messages/color_map_entries.py
wsvnc/server_messages/cut_text.py
wsvnc/server_messages/framebuffer_update.py
wsvnc/server_messages/server_message_interface.py
wsvnc/utils/__init__.py
wsvnc/utils/logger.py
wsvnc/utils/safe_transport.py
wsvnc/vnc/__init__.py
wsvnc/vnc/vnc_client.py
py_wsvnc-1.0.0.dist-info/LICENSE
py_wsvnc-1.0.0.dist-info/METADATA
py_wsvnc-1.0.0.dist-info/NOTICES
py_wsvnc-1.0.0.dist-info/WHEEL
py_wsvnc-1.0.0.dist-info/top_level.txt
py_wsvnc-1.0.0.dist-info/RECORD
