Metadata-Version: 2.1
Name: py-wsvnc
Version: 1.0.0
Summary: WebSocket VNC Client.
Author-email: Matthew Boyer <matthew.boyer@cynnovative.com>
License: MIT
Project-URL: homepage, https://github.com/Cynnovative/py-wsvnc
Requires-Python: >=3.10
License-File: LICENSE
License-File: NOTICES
Requires-Dist: websockets~=12.0
Requires-Dist: pillow~=10.4.0
Requires-Dist: pycryptodomex~=3.19.0
Provides-Extra: dev
Requires-Dist: docformatter[tomli]>=1.7.5; extra == "dev"
Requires-Dist: mypy; extra == "dev"
Requires-Dist: pytest>=7.4.1; extra == "dev"
Requires-Dist: ruff>=0.1.6; extra == "dev"
Requires-Dist: websockify>=0.11.0; extra == "dev"
Requires-Dist: types-Pillow>=10.1.0.1; extra == "dev"
Requires-Dist: coverage>=7.3.2; extra == "dev"
